{
  "kings-row": [
    {
      "id": "mowaxeo5-68b2",
      "mapKey": "kings-row",
      "worldX": -110.87598096499384,
      "worldY": 3.95,
      "worldZ": -17.897944792766648,
      "pixelX": 2134.3270467492493,
      "pixelY": 892.6483749322954,
      "screenshot": "/maps/spots/kings-row/mowaxeo5-68b2.jpg",
      "capturedAt": "2026-05-08T02:38:47.365Z",
      "sourceFilename": "20260507191635_1.jpg",
      "facingDeg": -93.75465172811953,
      "editedAt": "2026-05-16T07:02:38.539Z"
    },
    {
      "id": "mowaxesn-4fd2",
      "mapKey": "kings-row",
      "worldX": -106.78227239877332,
      "worldY": 2.53,
      "worldZ": -7.61988126658328,
      "pixelX": 2006.164368120248,
      "pixelY": 1225.6655143811,
      "screenshot": "/maps/spots/kings-row/mowaxesn-4fd2.jpg",
      "capturedAt": "2026-05-08T02:38:47.365Z",
      "sourceFilename": "20260507191623_1.jpg",
      "facingDeg": -65.23709427606286
    },
    {
      "id": "mowaxex4-abff",
      "mapKey": "kings-row",
      "worldX": -78.2771243750977,
      "worldY": 3.04,
      "worldZ": -44.124378184825936,
      "pixelX": 3275.540590758527,
      "pixelY": 1234.0860432923837,
      "screenshot": "/maps/spots/kings-row/mowaxex4-abff.jpg",
      "capturedAt": "2026-05-08T02:38:47.365Z",
      "sourceFilename": "20260507191610_1.jpg",
      "facingDeg": 158.73428119656575
    },
    {
      "id": "mowaxf1z-eba7",
      "mapKey": "kings-row",
      "worldX": -69.26351807348394,
      "worldY": 2.46,
      "worldZ": -22.393635657839685,
      "pixelX": 2942.73643403005,
      "pixelY": 1931.9086900652223,
      "screenshot": "/maps/spots/kings-row/mowaxf1z-eba7.jpg",
      "capturedAt": "2026-05-08T02:38:47.365Z",
      "sourceFilename": "20260507191548_1.jpg",
      "facingDeg": -121.81954425557116
    },
    {
      "id": "mowaxf6q-b8b3",
      "mapKey": "kings-row",
      "worldX": -60.904578150962365,
      "worldY": 3.4,
      "worldZ": -23.932403696356776,
      "pixelX": 3114.6256851459552,
      "pixelY": 2123.2905366684986,
      "screenshot": "/maps/spots/kings-row/mowaxf6q-b8b3.jpg",
      "capturedAt": "2026-05-08T02:38:47.365Z",
      "sourceFilename": "20260507191537_1.jpg",
      "facingDeg": -28.258029614706857
    },
    {
      "id": "mowaxfbq-c5f0",
      "mapKey": "kings-row",
      "worldX": 17.908196145151692,
      "worldY": 7.69,
      "worldZ": -38.63088541523017,
      "pixelX": 4692.174287518083,
      "pixelY": 3871.7970102193663,
      "screenshot": "/maps/spots/kings-row/mowaxfbq-c5f0.jpg",
      "capturedAt": "2026-05-08T02:38:47.365Z",
      "sourceFilename": "20260507191510_1.jpg",
      "facingDeg": -74.19748604606448
    },
    {
      "id": "mowaxfgf-62cd",
      "mapKey": "kings-row",
      "worldX": 8.648882892029903,
      "worldY": 2.23,
      "worldZ": 1.157438559380598,
      "pixelX": 3657.374333390153,
      "pixelY": 4187.324976866507,
      "screenshot": "/maps/spots/kings-row/mowaxfgf-62cd.jpg",
      "capturedAt": "2026-05-08T02:38:47.365Z",
      "sourceFilename": "20260507191452_1.jpg",
      "facingDeg": 99.31708606912645
    },
    {
      "id": "mowaxfl5-69c5",
      "mapKey": "kings-row",
      "worldX": 7.4755354733666195,
      "worldY": 7.95,
      "worldZ": 0.028378933039857782,
      "pixelX": 3663.7295755612913,
      "pixelY": 4147.118358252569,
      "screenshot": "/maps/spots/kings-row/mowaxfl5-69c5.jpg",
      "capturedAt": "2026-05-08T02:38:47.365Z",
      "sourceFilename": "20260507191443_1.jpg",
      "facingDeg": 119.21437998026845
    },
    {
      "id": "mowaxfps-762c",
      "mapKey": "kings-row",
      "worldX": -7.734141301672067,
      "worldY": 7.55,
      "worldZ": -41.15201002012205,
      "pixelX": 4364.7368221829165,
      "pixelY": 3196.765578310663,
      "screenshot": "/maps/spots/kings-row/mowaxfps-762c.jpg",
      "capturedAt": "2026-05-08T02:38:47.365Z",
      "sourceFilename": "20260507191431_1.jpg",
      "facingDeg": -127.84775828868396
    },
    {
      "id": "mowaxfv2-4763",
      "mapKey": "kings-row",
      "worldX": -26.324506649064123,
      "worldY": 7.62,
      "worldZ": -43.3910413926524,
      "pixelX": 4126.607256524507,
      "pixelY": 2677.771767434956,
      "screenshot": "/maps/spots/kings-row/mowaxfv2-4763.jpg",
      "capturedAt": "2026-05-08T02:38:47.365Z",
      "sourceFilename": "20260507191413_1.jpg",
      "facingDeg": -159.85276539197167
    },
    {
      "id": "mowaxg0a-71e9",
      "mapKey": "kings-row",
      "worldX": -31.48104165488351,
      "worldY": 3.07,
      "worldZ": -22.255137401114155,
      "pixelX": 3552.2856215547104,
      "pixelY": 2906.8383723767997,
      "screenshot": "/maps/spots/kings-row/mowaxg0a-71e9.jpg",
      "capturedAt": "2026-05-08T02:38:47.365Z",
      "sourceFilename": "20260507191401_1.jpg",
      "facingDeg": 162.93846878010368
    },
    {
      "id": "mowaxg5c-15ca",
      "mapKey": "kings-row",
      "worldX": -44.52920022007682,
      "worldY": 1.52,
      "worldZ": -34.52220313501625,
      "pixelX": 3620.815582824619,
      "pixelY": 2358.011912998453,
      "screenshot": "/maps/spots/kings-row/mowaxg5c-15ca.jpg",
      "capturedAt": "2026-05-08T02:38:47.365Z",
      "sourceFilename": "20260507191349_1.jpg",
      "facingDeg": -49.85309638699235
    },
    {
      "id": "mowaxgaf-7d04",
      "mapKey": "kings-row",
      "worldX": -50.601756049005665,
      "worldY": 1.72,
      "worldZ": -32.62254726409557,
      "pixelX": 3477.7140188604744,
      "pixelY": 2232.540726573726,
      "screenshot": "/maps/spots/kings-row/mowaxgaf-7d04.jpg",
      "capturedAt": "2026-05-08T02:38:47.365Z",
      "sourceFilename": "20260507191343_1.jpg",
      "facingDeg": -113.50737115005452
    },
    {
      "id": "mowaxgfa-5563",
      "mapKey": "kings-row",
      "worldX": -60.62,
      "worldY": 2.61,
      "worldZ": -49.12,
      "pixelX": 3700.163369355931,
      "pixelY": 1629.6319798668203,
      "screenshot": "/maps/spots/kings-row/mowaxgfa-5563.jpg",
      "capturedAt": "2026-05-08T02:38:47.365Z",
      "sourceFilename": "20260507191332_1.jpg",
      "facingDeg": -86.88923913260098
    },
    {
      "id": "mowaxgks-c574",
      "mapKey": "kings-row",
      "worldX": -81.7622257069045,
      "worldY": 1.57,
      "worldZ": 12.216286155208472,
      "pixelX": 2058.8145276138443,
      "pixelY": 2244.2678260861935,
      "screenshot": "/maps/spots/kings-row/mowaxgks-c574.jpg",
      "capturedAt": "2026-05-08T02:38:47.365Z",
      "sourceFilename": "20260507191250_1.jpg",
      "facingDeg": 80.43671617045693
    },
    {
      "id": "mowaxgpc-4728",
      "mapKey": "kings-row",
      "worldX": -92.40747142702038,
      "worldY": 3.57,
      "worldZ": 9.810137258508544,
      "pixelX": 1927.66652846228,
      "pixelY": 1937.9066520291813,
      "screenshot": "/maps/spots/kings-row/mowaxgpc-4728.jpg",
      "capturedAt": "2026-05-08T02:38:47.365Z",
      "sourceFilename": "20260507191237_1.jpg",
      "facingDeg": 138.9301755457255
    },
    {
      "id": "mowaxguq-a58a",
      "mapKey": "kings-row",
      "worldX": -102.54769727317507,
      "worldY": 2.4,
      "worldZ": -9.487252121963984,
      "pixelX": 2115.2188766075947,
      "pixelY": 1300.8656838515508,
      "screenshot": "/maps/spots/kings-row/mowaxguq-a58a.jpg",
      "capturedAt": "2026-05-08T02:38:47.365Z",
      "sourceFilename": "20260507191222_1.jpg",
      "facingDeg": -95.93893777848452
    },
    {
      "id": "mowaxgzd-3b66",
      "mapKey": "kings-row",
      "worldX": -137.04138605555232,
      "worldY": 7.72,
      "worldZ": 24.02966976514023,
      "pixelX": 933.6937359893452,
      "pixelY": 1077.136132984191,
      "screenshot": "/maps/spots/kings-row/mowaxgzd-3b66.jpg",
      "capturedAt": "2026-05-08T02:38:47.365Z",
      "sourceFilename": "20260507191142_1.jpg",
      "facingDeg": -21.12711025225014
    },
    {
      "id": "mowaxh49-a5a4",
      "mapKey": "kings-row",
      "worldX": -142.51149925053,
      "worldY": 7.8,
      "worldZ": 25.278712679804123,
      "pixelX": 819.3301605657607,
      "pixelY": 961.4227045619652,
      "screenshot": "/maps/spots/kings-row/mowaxh49-a5a4.jpg",
      "capturedAt": "2026-05-08T02:38:47.365Z",
      "sourceFilename": "20260507191133_1.jpg",
      "facingDeg": 98.7766862862419,
      "editedAt": "2026-05-19T22:23:16.196Z"
    },
    {
      "id": "mowaxh93-e2e9",
      "mapKey": "kings-row",
      "worldX": -133.9847034909774,
      "worldY": 1.04,
      "worldZ": 2.2164534019362847,
      "pixelX": 1348.7140501406805,
      "pixelY": 699.1968723456495,
      "screenshot": "/maps/spots/kings-row/mowaxh93-e2e9.jpg",
      "capturedAt": "2026-05-08T02:38:47.365Z",
      "sourceFilename": "20260507191115_1.jpg",
      "facingDeg": 130.62866935621915
    },
    {
      "id": "mowaxheh-0cc5",
      "mapKey": "kings-row",
      "worldX": -121.90577108394795,
      "worldY": 2.3,
      "worldZ": -8.590305563975376,
      "pixelX": 1759.033327166284,
      "pixelY": 792.4085364681106,
      "screenshot": "/maps/spots/kings-row/mowaxheh-0cc5.jpg",
      "capturedAt": "2026-05-08T02:38:47.365Z",
      "sourceFilename": "20260507191059_1.jpg",
      "facingDeg": -121.01041432266643
    },
    {
      "id": "mowaxhkp-905b",
      "mapKey": "kings-row",
      "worldX": -105.53314517917542,
      "worldY": 7.93,
      "worldZ": -4.921587616532152,
      "pixelX": 1976.6748396938283,
      "pixelY": 1314.7481665342168,
      "screenshot": "/maps/spots/kings-row/mowaxhkp-905b.jpg",
      "capturedAt": "2026-05-08T02:38:47.365Z",
      "sourceFilename": "20260507191043_1.jpg",
      "facingDeg": 121.8540716350526,
      "editedAt": "2026-05-19T22:25:04.361Z"
    },
    {
      "id": "mowaxhoh-17b2",
      "mapKey": "kings-row",
      "worldX": -105.47972399090528,
      "worldY": 6.43,
      "worldZ": -4.9640490966184565,
      "pixelX": 1978.3947365371102,
      "pixelY": 1315.3038138928193,
      "screenshot": "/maps/spots/kings-row/mowaxhoh-17b2.jpg",
      "capturedAt": "2026-05-08T02:38:47.365Z",
      "sourceFilename": "20260507191040_1.jpg",
      "facingDeg": 137.8038752474129,
      "editedAt": "2026-05-19T22:25:20.849Z"
    },
    {
      "id": "mowaxht8-a42a",
      "mapKey": "kings-row",
      "worldX": -77.87082332562849,
      "worldY": 4.23,
      "worldZ": -40.51607098082614,
      "pixelX": 3198.550891147245,
      "pixelY": 1324.9580216795257,
      "screenshot": "/maps/spots/kings-row/mowaxht8-a42a.jpg",
      "capturedAt": "2026-05-08T02:38:47.365Z",
      "sourceFilename": "20260507191019_1.jpg",
      "facingDeg": -105.8454469756811
    },
    {
      "id": "mowaxhx5-b0f6",
      "mapKey": "kings-row",
      "worldX": -64.24315285688608,
      "worldY": 1.31,
      "worldZ": -22.157750877366087,
      "pixelX": 3021.1589597130633,
      "pixelY": 2068.8986605788327,
      "screenshot": "/maps/spots/kings-row/mowaxhx5-b0f6.jpg",
      "capturedAt": "2026-05-08T02:38:47.365Z",
      "sourceFilename": "20260507190959_1.jpg",
      "facingDeg": -87.1683229590324,
      "editedAt": "2026-05-19T22:27:02.503Z"
    },
    {
      "id": "mowaxi2b-5a0d",
      "mapKey": "kings-row",
      "worldX": -70.23,
      "worldY": 2.4,
      "worldZ": -31.25,
      "pixelX": 3119.4773696993143,
      "pixelY": 1731.50866841315,
      "screenshot": "/maps/spots/kings-row/mowaxi2b-5a0d.jpg",
      "capturedAt": "2026-05-08T02:38:47.365Z",
      "sourceFilename": "20260507190945_1.jpg",
      "facingDeg": 51.0244111587749,
      "editedAt": "2026-05-19T22:27:17.978Z"
    },
    {
      "id": "mowaxi7b-8448",
      "mapKey": "kings-row",
      "worldX": -64.94476267283048,
      "worldY": 2.12,
      "worldZ": -35.681457568169044,
      "pixelX": 3308.711328514398,
      "pixelY": 1786.5832162124927,
      "screenshot": "/maps/spots/kings-row/mowaxi7b-8448.jpg",
      "capturedAt": "2026-05-08T02:38:47.365Z",
      "sourceFilename": "20260507190926_1.jpg",
      "editedAt": "2026-05-19T22:27:36.602Z",
      "facingDeg": -65.65599898824074
    },
    {
      "id": "mowaxibu-8ea7",
      "mapKey": "kings-row",
      "worldX": -58.05052394285043,
      "worldY": -0.09,
      "worldZ": -45.72342380059477,
      "pixelX": 3661.1570846237078,
      "pixelY": 1772.7552780402805,
      "screenshot": "/maps/spots/kings-row/mowaxibu-8ea7.jpg",
      "capturedAt": "2026-05-08T02:38:47.365Z",
      "sourceFilename": "20260507190911_1.jpg",
      "editedAt": "2026-05-19T22:27:58.791Z",
      "facingDeg": -7.439208621840864
    },
    {
      "id": "mowaxihj-4fc1",
      "mapKey": "kings-row",
      "worldX": -31.640719883475086,
      "worldY": 8.5,
      "worldZ": -32.64704601833418,
      "pixelX": 3785.2380887811287,
      "pixelY": 2727.5764030185933,
      "screenshot": "/maps/spots/kings-row/mowaxihj-4fc1.jpg",
      "capturedAt": "2026-05-08T02:38:47.365Z",
      "sourceFilename": "20260507190857_1.jpg",
      "editedAt": "2026-05-19T22:28:19.411Z",
      "facingDeg": 60.79690661597011
    },
    {
      "id": "mowaximd-f4ff",
      "mapKey": "kings-row",
      "worldX": 11.01654620533552,
      "worldY": 5.77,
      "worldZ": -18.852471388386565,
      "pixelX": 4123.263944364501,
      "pixelY": 3981.8941569840076,
      "screenshot": "/maps/spots/kings-row/mowaximd-f4ff.jpg",
      "capturedAt": "2026-05-08T02:38:47.365Z",
      "sourceFilename": "20260507190830_1.jpg",
      "editedAt": "2026-05-19T22:28:56.998Z",
      "facingDeg": 8.895352968590835
    },
    {
      "id": "mowaxiqv-f035",
      "mapKey": "kings-row",
      "worldX": -15.430757317201717,
      "worldY": 1.74,
      "worldZ": -17.400232245136156,
      "pixelX": 3694.293816707555,
      "pixelY": 3376.9153266797084,
      "screenshot": "/maps/spots/kings-row/mowaxiqv-f035.jpg",
      "capturedAt": "2026-05-08T02:38:47.365Z",
      "sourceFilename": "20260507190814_1.jpg",
      "editedAt": "2026-05-19T22:29:14.574Z",
      "facingDeg": -22.203478532057396
    },
    {
      "id": "mowaxiv0-fb86",
      "mapKey": "kings-row",
      "worldX": -27.684139530182442,
      "worldY": 13.6,
      "worldZ": -37.90755763925099,
      "pixelX": 3972.1807734505387,
      "pixelY": 2738.658515203816,
      "screenshot": "/maps/spots/kings-row/mowaxiv0-fb86.jpg",
      "capturedAt": "2026-05-08T02:38:47.365Z",
      "sourceFilename": "20260507190745_1.jpg",
      "editedAt": "2026-05-19T22:56:39.145Z",
      "facingDeg": 175.31410016049728
    },
    {
      "id": "mowaxizk-9099",
      "mapKey": "kings-row",
      "worldX": -10.240026275161583,
      "worldY": 2.37,
      "worldZ": -48.49579647290685,
      "pixelX": 4509.311007998506,
      "pixelY": 3010.5471544384854,
      "screenshot": "/maps/spots/kings-row/mowaxizk-9099.jpg",
      "capturedAt": "2026-05-08T02:38:47.365Z",
      "sourceFilename": "20260507185629_1.jpg",
      "editedAt": "2026-05-19T22:30:00.904Z",
      "facingDeg": 22.421123338947112
    },
    {
      "id": "mowaxj49-e700",
      "mapKey": "kings-row",
      "worldX": -94.59743989823829,
      "worldY": 5.06,
      "worldZ": -16.184047485914512,
      "pixelX": 2384.3655630397275,
      "pixelY": 1377.059281573601,
      "screenshot": "/maps/spots/kings-row/mowaxj49-e700.jpg",
      "capturedAt": "2026-05-08T02:38:47.365Z",
      "sourceFilename": "20260507181847_1.jpg",
      "editedAt": "2026-05-19T22:30:20.622Z",
      "facingDeg": 162.73923392555363
    },
    {
      "id": "mowbantd-d2b5",
      "mapKey": "kings-row",
      "worldX": -135.3609587931705,
      "worldY": 2.43,
      "worldZ": 22.91641248876949,
      "pixelX": 980.3078795480815,
      "pixelY": 1097.9814686721968,
      "screenshot": "/maps/spots/kings-row/mowbantd-d2b5.jpg",
      "capturedAt": "2026-05-08T02:46:47.771Z",
      "sourceFilename": "20260507194409_1.jpg",
      "editedAt": "2026-05-19T22:31:09.207Z",
      "facingDeg": -5.494305944528974
    },
    {
      "id": "mowbanyd-3d7f",
      "mapKey": "kings-row",
      "worldX": -133.79677817181545,
      "worldY": 0.08,
      "worldZ": 13.410784142335563,
      "pixelX": 1161.5752927780677,
      "pixelY": 944.0445543334379,
      "screenshot": "/maps/spots/kings-row/mowbanyd-3d7f.jpg",
      "capturedAt": "2026-05-08T02:46:47.771Z",
      "sourceFilename": "20260507194358_1.jpg",
      "editedAt": "2026-05-19T22:31:39.353Z",
      "facingDeg": 32.02526376922634
    },
    {
      "id": "mowbao33-b553",
      "mapKey": "kings-row",
      "worldX": -131.28904057552293,
      "worldY": 7.68,
      "worldZ": 7.649633507706686,
      "pixelX": 1302.5629029791498,
      "pixelY": 889.3696934946114,
      "screenshot": "/maps/spots/kings-row/mowbao33-b553.jpg",
      "capturedAt": "2026-05-08T02:46:47.771Z",
      "sourceFilename": "20260507194349_1.jpg",
      "editedAt": "2026-05-19T22:32:11.784Z",
      "facingDeg": 120.87208336308032
    },
    {
      "id": "mowbao7p-0c2f",
      "mapKey": "kings-row",
      "worldX": -92.92852589402318,
      "worldY": 115,
      "worldZ": -1.4307493727964513,
      "pixelX": 2125.469337599679,
      "pixelY": 1714.8197633355917,
      "screenshot": "/maps/spots/kings-row/mowbao7p-0c2f.jpg",
      "capturedAt": "2026-05-08T02:46:47.771Z",
      "sourceFilename": "20260507194340_1.jpg",
      "editedAt": "2026-05-19T22:32:31.527Z",
      "facingDeg": -21.242716521385503
    },
    {
      "id": "mowbaodc-6cf1",
      "mapKey": "kings-row",
      "worldX": -99.04011823331582,
      "worldY": 3.57,
      "worldZ": -6.341284969865164,
      "pixelX": 2115.036923714913,
      "pixelY": 1458.5023985847497,
      "screenshot": "/maps/spots/kings-row/mowbaodc-6cf1.jpg",
      "capturedAt": "2026-05-08T02:46:47.771Z",
      "sourceFilename": "20260507194332_1.jpg",
      "editedAt": "2026-05-19T22:32:53.612Z",
      "facingDeg": 137.11753477675472
    },
    {
      "id": "mowbaohw-e6ca",
      "mapKey": "kings-row",
      "worldX": -106.73001091978648,
      "worldY": 2.03,
      "worldZ": -4.7254894326065155,
      "pixelX": 1952.3502334216012,
      "pixelY": 1286.8506017304383,
      "screenshot": "/maps/spots/kings-row/mowbaohw-e6ca.jpg",
      "capturedAt": "2026-05-08T02:46:47.771Z",
      "sourceFilename": "20260507194327_1.jpg",
      "editedAt": "2026-05-19T22:33:43.540Z",
      "facingDeg": -56.12410897578219
    },
    {
      "id": "mowbaomx-5223",
      "mapKey": "kings-row",
      "worldX": -60.47023236643987,
      "worldY": 6.2,
      "worldZ": -14.697936606718947,
      "pixelX": 2925.68470947101,
      "pixelY": 2303.7709789844876,
      "screenshot": "/maps/spots/kings-row/mowbaomx-5223.jpg",
      "capturedAt": "2026-05-08T02:46:47.771Z",
      "sourceFilename": "20260507194312_1.jpg",
      "editedAt": "2026-05-19T22:34:30.288Z",
      "facingDeg": -20.679588516222275
    },
    {
      "id": "mowbaorw-5bca",
      "mapKey": "kings-row",
      "worldX": -75.32680529840385,
      "worldY": 1.49,
      "worldZ": -42.971156198199544,
      "pixelX": 3299.794503005626,
      "pixelY": 1343.8380621611952,
      "screenshot": "/maps/spots/kings-row/mowbaorw-5bca.jpg",
      "capturedAt": "2026-05-08T02:46:47.771Z",
      "sourceFilename": "20260507194258_1.jpg",
      "editedAt": "2026-05-19T22:35:08.588Z",
      "facingDeg": 161.7117750036308
    },
    {
      "id": "mowbaox3-21e9",
      "mapKey": "kings-row",
      "worldX": -87.0676906610609,
      "worldY": 2.81,
      "worldZ": -35.64434855503138,
      "pixelX": 2927.6855912452284,
      "pixelY": 1170.5796725389473,
      "screenshot": "/maps/spots/kings-row/mowbaox3-21e9.jpg",
      "capturedAt": "2026-05-08T02:46:47.772Z",
      "sourceFilename": "20260507194247_1.jpg",
      "editedAt": "2026-05-19T22:38:44.792Z",
      "facingDeg": -161.9507312272721
    },
    {
      "id": "mowbap1h-00e7",
      "mapKey": "kings-row",
      "worldX": -87.1046703775068,
      "worldY": 1.31,
      "worldZ": -35.618392520259704,
      "pixelX": 2926.4592893256718,
      "pixelY": 1170.1020581158364,
      "screenshot": "/maps/spots/kings-row/mowbap1h-00e7.jpg",
      "capturedAt": "2026-05-08T02:46:47.772Z",
      "sourceFilename": "20260507194245_1.jpg",
      "editedAt": "2026-05-19T22:39:14.659Z",
      "facingDeg": -153.8905716601841
    },
    {
      "id": "mowbap6n-60c3",
      "mapKey": "kings-row",
      "worldX": -61.32021228960345,
      "worldY": 1.3,
      "worldZ": -34.386118762320265,
      "pixelX": 3340.10474997508,
      "pixelY": 1911.1881790809357,
      "screenshot": "/maps/spots/kings-row/mowbap6n-60c3.jpg",
      "capturedAt": "2026-05-08T02:46:47.772Z",
      "sourceFilename": "20260507194236_1.jpg",
      "editedAt": "2026-05-19T22:39:51.107Z",
      "facingDeg": -113.52461868412063
    },
    {
      "id": "mowbapbm-20dd",
      "mapKey": "kings-row",
      "worldX": -29.37550489493709,
      "worldY": 10.57,
      "worldZ": -35.107683780343784,
      "pixelX": 3878.8584722670503,
      "pixelY": 2743.4475707633815,
      "screenshot": "/maps/spots/kings-row/mowbapbm-20dd.jpg",
      "capturedAt": "2026-05-08T02:46:47.772Z",
      "sourceFilename": "20260507194228_1.jpg",
      "editedAt": "2026-05-19T22:40:15.401Z",
      "facingDeg": 166.24306052392004
    },
    {
      "id": "mowbapgh-2545",
      "mapKey": "kings-row",
      "worldX": -32.779394398225556,
      "worldY": 10.57,
      "worldZ": -34.77807919385293,
      "pixelX": 3816.7254147578174,
      "pixelY": 2661.0494595916916,
      "screenshot": "/maps/spots/kings-row/mowbapgh-2545.jpg",
      "capturedAt": "2026-05-08T02:46:47.772Z",
      "sourceFilename": "20260507194224_1.jpg",
      "editedAt": "2026-05-19T22:57:02.583Z",
      "facingDeg": -30.00035328636998
    },
    {
      "id": "mowbaplm-3c29",
      "mapKey": "kings-row",
      "worldX": -44.940354376849264,
      "worldY": 1.41,
      "worldZ": -33.68147910832938,
      "pixelX": 3594.680905986562,
      "pixelY": 2362.6214165074825,
      "screenshot": "/maps/spots/kings-row/mowbaplm-3c29.jpg",
      "capturedAt": "2026-05-08T02:46:47.772Z",
      "sourceFilename": "20260507194218_1.jpg",
      "editedAt": "2026-05-19T22:57:15.293Z",
      "facingDeg": -44.406897174141186
    },
    {
      "id": "mowbapqn-a96c",
      "mapKey": "kings-row",
      "worldX": -32.48668828201542,
      "worldY": 8.5,
      "worldZ": -35.78381576301352,
      "pixelX": 3845.0326821005497,
      "pixelY": 2650.9865324170855,
      "screenshot": "/maps/spots/kings-row/mowbapqn-a96c.jpg",
      "capturedAt": "2026-05-08T02:46:47.772Z",
      "sourceFilename": "20260507194213_1.jpg",
      "editedAt": "2026-05-19T22:57:32.475Z",
      "facingDeg": -54.67565059922519
    },
    {
      "id": "mowbapvj-e7c3",
      "mapKey": "kings-row",
      "worldX": -30.480733482256404,
      "worldY": -0.4,
      "worldZ": -25.13033375627315,
      "pixelX": 3632.1072068526305,
      "pixelY": 2884.4026419329616,
      "screenshot": "/maps/spots/kings-row/mowbapvj-e7c3.jpg",
      "capturedAt": "2026-05-08T02:46:47.772Z",
      "sourceFilename": "20260507194203_1.jpg",
      "editedAt": "2026-05-19T22:58:00.656Z",
      "facingDeg": 123.75012597307445
    },
    {
      "id": "mowbaq0d-3071",
      "mapKey": "kings-row",
      "worldX": -24.736282069797902,
      "worldY": 8.42,
      "worldZ": -43.25776825219667,
      "pixelX": 4148.749397318958,
      "pixelY": 2721.9039716238635,
      "screenshot": "/maps/spots/kings-row/mowbaq0d-3071.jpg",
      "capturedAt": "2026-05-08T02:46:47.772Z",
      "sourceFilename": "20260507194151_1.jpg",
      "editedAt": "2026-05-19T22:58:22.285Z",
      "facingDeg": -119.19707852137816
    },
    {
      "id": "mowbaq51-1322",
      "mapKey": "kings-row",
      "worldX": -11.480767189096799,
      "worldY": 1.8,
      "worldZ": -37.60362206668538,
      "pixelX": 4220.069902777996,
      "pixelY": 3159.2259142379803,
      "screenshot": "/maps/spots/kings-row/mowbaq51-1322.jpg",
      "capturedAt": "2026-05-08T02:46:47.772Z",
      "sourceFilename": "20260507194144_1.jpg",
      "editedAt": "2026-05-19T22:58:36.986Z",
      "facingDeg": -69.88835920277198
    },
    {
      "id": "mowbaq9w-709d",
      "mapKey": "kings-row",
      "worldX": -7.127792971848323,
      "worldY": 5.67,
      "worldZ": -49.975404273701685,
      "pixelX": 4595.922100507201,
      "pixelY": 3066.617835032223,
      "screenshot": "/maps/spots/kings-row/mowbaq9w-709d.jpg",
      "capturedAt": "2026-05-08T02:46:47.772Z",
      "sourceFilename": "20260507194130_1.jpg",
      "facingDeg": 7.063643777079376,
      "editedAt": "2026-05-19T22:58:56.114Z"
    },
    {
      "id": "mowbaqds-eecf",
      "mapKey": "kings-row",
      "worldX": 0.8189329296627063,
      "worldY": 7.44,
      "worldZ": -42.392186839805895,
      "pixelX": 4527.378491118693,
      "pixelY": 3393.3132690045377,
      "screenshot": "/maps/spots/kings-row/mowbaqds-eecf.jpg",
      "capturedAt": "2026-05-08T02:46:47.772Z",
      "sourceFilename": "20260507194123_1.jpg",
      "editedAt": "2026-05-19T22:59:20.890Z",
      "facingDeg": -80.02060020841577
    },
    {
      "id": "mowbaqka-ef17",
      "mapKey": "kings-row",
      "worldX": -4.8772512406869675,
      "worldY": 1.45,
      "worldZ": -32.03267063060764,
      "pixelX": 4188.8623962052825,
      "pixelY": 3411.995882453965,
      "screenshot": "/maps/spots/kings-row/mowbaqka-ef17.jpg",
      "capturedAt": "2026-05-08T02:46:47.772Z",
      "sourceFilename": "20260507194114_1.jpg",
      "editedAt": "2026-05-19T23:00:04.876Z",
      "facingDeg": 71.69246930545333
    },
    {
      "id": "mowbaqpi-9edc",
      "mapKey": "kings-row",
      "worldX": -0.08724650138827988,
      "worldY": 1.45,
      "worldZ": -31.469770528914676,
      "pixelX": 4248.527589083105,
      "pixelY": 3538.1394831508765,
      "screenshot": "/maps/spots/kings-row/mowbaqpi-9edc.jpg",
      "capturedAt": "2026-05-08T02:46:47.772Z",
      "sourceFilename": "20260507194109_1.jpg",
      "editedAt": "2026-05-19T23:00:16.521Z",
      "facingDeg": -45.4014653582044
    },
    {
      "id": "mowbaqu2-646f",
      "mapKey": "kings-row",
      "worldX": 9.57,
      "worldY": 2.31,
      "worldZ": -1.16,
      "pixelX": 3718.748258847056,
      "pixelY": 4178.796234051159,
      "screenshot": "/maps/spots/kings-row/mowbaqu2-646f.jpg",
      "capturedAt": "2026-05-08T02:46:47.772Z",
      "sourceFilename": "20260507194053_1.jpg",
      "facingDeg": 126.26165095755813,
      "editedAt": "2026-05-19T23:00:43.038Z"
    },
    {
      "id": "mowbaqyj-18a3",
      "mapKey": "kings-row",
      "worldX": 5.447595309721909,
      "worldY": 1.7,
      "worldZ": -10.030251950449946,
      "pixelX": 3846.7924754694586,
      "pixelY": 3971.281893756329,
      "screenshot": "/maps/spots/kings-row/mowbaqyj-18a3.jpg",
      "capturedAt": "2026-05-08T02:46:47.772Z",
      "sourceFilename": "20260507194048_1.jpg",
      "editedAt": "2026-05-19T23:01:12.642Z",
      "facingDeg": 86.49646835521554
    },
    {
      "id": "mowbar3q-9974",
      "mapKey": "kings-row",
      "worldX": -1.1532972489344693,
      "worldY": 0.95,
      "worldZ": -15.109606686881433,
      "pixelX": 3859.6229813599116,
      "pixelY": 3749.2080560362288,
      "screenshot": "/maps/spots/kings-row/mowbar3q-9974.jpg",
      "capturedAt": "2026-05-08T02:46:47.772Z",
      "sourceFilename": "20260507194036_1.jpg",
      "editedAt": "2026-05-19T23:01:24.565Z",
      "facingDeg": 3.6872957680463823
    },
    {
      "id": "mowbar8b-00ca",
      "mapKey": "kings-row",
      "worldX": 8.791301936243398,
      "worldY": 1.1,
      "worldZ": 11.10317981193698,
      "pixelX": 3458.4758383590965,
      "pixelY": 4311.884984628054,
      "screenshot": "/maps/spots/kings-row/mowbar8b-00ca.jpg",
      "capturedAt": "2026-05-08T02:46:47.772Z",
      "sourceFilename": "20260507194021_1.jpg",
      "editedAt": "2026-05-19T23:01:38.813Z",
      "facingDeg": -21.829715036298982
    },
    {
      "id": "mowbardf-cc7d",
      "mapKey": "kings-row",
      "worldX": 8.898457949349575,
      "worldY": -0.4,
      "worldZ": 10.997502509076208,
      "pixelX": 3462.098683235228,
      "pixelY": 4312.937631646357,
      "screenshot": "/maps/spots/kings-row/mowbardf-cc7d.jpg",
      "capturedAt": "2026-05-08T02:46:47.772Z",
      "sourceFilename": "20260507194019_1.jpg",
      "editedAt": "2026-05-19T23:01:44.616Z",
      "facingDeg": -21.638901633390066
    },
    {
      "id": "mowbarit-d97c",
      "mapKey": "kings-row",
      "worldX": -3.2504693949503265,
      "worldY": 15.06,
      "worldZ": 18.29984279471418,
      "pixelX": 3146.0756460436774,
      "pixelY": 4138.816457619831,
      "screenshot": "/maps/spots/kings-row/mowbarit-d97c.jpg",
      "capturedAt": "2026-05-08T02:46:47.772Z",
      "sourceFilename": "20260507194008_1.jpg",
      "editedAt": "2026-05-19T23:01:57.478Z",
      "facingDeg": 53.68224659459128
    }
  ],
  "blizzard-world": [
    {
      "id": "mp7hmj9q-8cab",
      "mapKey": "blizzard-world",
      "worldX": -93.1205288370033,
      "worldY": -1.06,
      "worldZ": 106.30929558734874,
      "pixelX": 3399.676788886059,
      "pixelY": 1810.9901448190965,
      "worldRotX": -0.96,
      "worldRotY": 0.11,
      "worldRotZ": 0.26,
      "facingDeg": 79.5625246488817,
      "screenshot": "/maps/spots/blizzard-world/mp7hmj9q-8cab.jpg",
      "capturedAt": "2026-05-16T00:10:31.463Z",
      "sourceFilename": "20260513170935_1.jpg"
    },
    {
      "id": "mp7hmjfi-28aa",
      "mapKey": "blizzard-world",
      "worldX": -93.99350098179715,
      "worldY": 0.64,
      "worldZ": 107.75811657281785,
      "pixelX": 3419.88662256113,
      "pixelY": 1775.7827712424007,
      "worldRotX": -0.94,
      "worldRotY": -0.14,
      "worldRotZ": 0.33,
      "facingDeg": 51.84277341263095,
      "screenshot": "/maps/spots/blizzard-world/mp7hmjfi-28aa.jpg",
      "capturedAt": "2026-05-16T00:10:31.463Z",
      "sourceFilename": "20260513170912_1.jpg"
    },
    {
      "id": "mp7hmjlf-d8c9",
      "mapKey": "blizzard-world",
      "worldX": -93.99095975286713,
      "worldY": -0.01,
      "worldZ": 107.68986523262639,
      "pixelX": 3419.88662256113,
      "pixelY": 1777.4955426545732,
      "worldRotX": 0.48,
      "worldRotY": 0.08,
      "worldRotZ": 0.88,
      "facingDeg": -58.017095591299174,
      "screenshot": "/maps/spots/blizzard-world/mp7hmjlf-d8c9.jpg",
      "capturedAt": "2026-05-16T00:10:31.463Z",
      "sourceFilename": "20260513170853_1.jpg"
    },
    {
      "id": "mp7hmjrn-efc4",
      "mapKey": "blizzard-world",
      "worldX": -113.91,
      "worldY": -0.51,
      "worldZ": 102.69,
      "pixelX": 3929.183917048179,
      "pixelY": 1934.6468615650288,
      "worldRotX": 0.72,
      "worldRotY": 0.03,
      "worldRotZ": 0.69,
      "facingDeg": -45.42313168042369,
      "screenshot": "/maps/spots/blizzard-world/mp7hmjrn-efc4.jpg",
      "capturedAt": "2026-05-16T00:10:31.463Z",
      "sourceFilename": "20260513170841_1.jpg"
    },
    {
      "id": "mp7hmjxf-f72e",
      "mapKey": "blizzard-world",
      "worldX": -125.91962979676381,
      "worldY": 0.85,
      "worldZ": 109.14679093055452,
      "pixelX": 4237.961247980497,
      "pixelY": 1785.1543260443714,
      "worldRotX": -0.94,
      "worldRotY": 0.21,
      "worldRotZ": -0.27,
      "facingDeg": 108.30204828521408,
      "screenshot": "/maps/spots/blizzard-world/mp7hmjxf-f72e.jpg",
      "capturedAt": "2026-05-16T00:10:31.463Z",
      "sourceFilename": "20260513170827_1.jpg"
    },
    {
      "id": "mp7hmk39-11e4",
      "mapKey": "blizzard-world",
      "worldX": -130.34237889230832,
      "worldY": -0.67,
      "worldZ": 136.69555505358494,
      "pixelX": 4323.194164512112,
      "pixelY": 1072.938832837802,
      "worldRotX": 0.7,
      "worldRotY": 0.12,
      "worldRotZ": -0.7,
      "facingDeg": -134.83686645264578,
      "screenshot": "/maps/spots/blizzard-world/mp7hmk39-11e4.jpg",
      "capturedAt": "2026-05-16T00:10:31.463Z",
      "sourceFilename": "20260513170811_1.jpg"
    },
    {
      "id": "mp7hmk90-9cff",
      "mapKey": "blizzard-world",
      "worldX": -114.53512726226447,
      "worldY": -0.27,
      "worldZ": 132.89432900766025,
      "pixelX": 3912.814048204093,
      "pixelY": 1160.9653248247673,
      "worldRotX": 0.27,
      "worldRotY": 0.17,
      "worldRotZ": -0.95,
      "facingDeg": -160.09625046269218,
      "screenshot": "/maps/spots/blizzard-world/mp7hmk90-9cff.jpg",
      "capturedAt": "2026-05-16T00:10:31.463Z",
      "sourceFilename": "20260513170803_1.jpg"
    },
    {
      "id": "mp7hmkep-f852",
      "mapKey": "blizzard-world",
      "worldX": -133.2547622715755,
      "worldY": 1.75,
      "worldZ": 151.05423398391312,
      "pixelX": 4383.733585069027,
      "pixelY": 702.9981676006541,
      "worldRotX": -0.97,
      "worldRotY": 0.06,
      "worldRotZ": -0.24,
      "facingDeg": 118.96766064606412,
      "screenshot": "/maps/spots/blizzard-world/mp7hmkep-f852.jpg",
      "capturedAt": "2026-05-16T00:10:31.463Z",
      "sourceFilename": "20260513170737_1.jpg"
    },
    {
      "id": "mp7hmkl6-81ef",
      "mapKey": "blizzard-world",
      "worldX": -137.54633409903562,
      "worldY": 3.02,
      "worldZ": 144.72322317721427,
      "pixelX": 4507.357661460126,
      "pixelY": 867.7337999192522,
      "worldRotX": -0.39,
      "worldRotY": 0.01,
      "worldRotZ": -0.92,
      "facingDeg": 158.34401096157717,
      "screenshot": "/maps/spots/blizzard-world/mp7hmkl6-81ef.jpg",
      "capturedAt": "2026-05-16T00:10:31.463Z",
      "sourceFilename": "20260513170714_1.jpg"
    },
    {
      "id": "mp7hmkqv-1917",
      "mapKey": "blizzard-world",
      "worldX": -108.79390583967573,
      "worldY": 6.45,
      "worldZ": 133.14915998914216,
      "pixelX": 3765.778635496907,
      "pixelY": 1150.823931888206,
      "worldRotX": 0.1,
      "worldRotY": -0.13,
      "worldRotZ": 0.99,
      "facingDeg": -10.60145239126114,
      "screenshot": "/maps/spots/blizzard-world/mp7hmkqv-1917.jpg",
      "capturedAt": "2026-05-16T00:10:31.463Z",
      "sourceFilename": "20260513170634_1.jpg"
    },
    {
      "id": "mp7hmkwk-58af",
      "mapKey": "blizzard-world",
      "worldX": -114.72000311589,
      "worldY": -0.14,
      "worldZ": 147.89344227143542,
      "pixelX": 3901.5570339474866,
      "pixelY": 781.0286162420496,
      "worldRotX": -0.96,
      "worldRotY": 0.11,
      "worldRotZ": -0.27,
      "facingDeg": 105.70863782901576,
      "screenshot": "/maps/spots/blizzard-world/mp7hmkwk-58af.jpg",
      "capturedAt": "2026-05-16T00:10:31.463Z",
      "sourceFilename": "20260513170618_1.jpg"
    },
    {
      "id": "mp7hml2p-4091",
      "mapKey": "blizzard-world",
      "worldX": -88.14961699451592,
      "worldY": 1.58,
      "worldZ": 105.38252429091513,
      "pixelX": 3278.675868020918,
      "pixelY": 1827.1495487597472,
      "worldRotX": -0.72,
      "worldRotY": 0.04,
      "worldRotZ": 0.69,
      "facingDeg": 46.33739741328261,
      "screenshot": "/maps/spots/blizzard-world/mp7hml2p-4091.jpg",
      "capturedAt": "2026-05-16T00:10:31.463Z",
      "sourceFilename": "20260513170546_1.jpg"
    },
    {
      "id": "mp7hml8v-793a",
      "mapKey": "blizzard-world",
      "worldX": -65.28501544822953,
      "worldY": 1.9,
      "worldZ": 136.4924204126394,
      "pixelX": 2714.3561792327455,
      "pixelY": 1044.5552633648283,
      "worldRotX": -0.74,
      "worldRotY": 0.34,
      "worldRotZ": -0.59,
      "facingDeg": 129.87100391583164,
      "screenshot": "/maps/spots/blizzard-world/mp7hml8v-793a.jpg",
      "capturedAt": "2026-05-16T00:10:31.463Z",
      "sourceFilename": "20260513170531_1.jpg"
    },
    {
      "id": "mp7hmleu-816b",
      "mapKey": "blizzard-world",
      "worldX": -65.09746915147981,
      "worldY": 3.02,
      "worldZ": 149.43220934822412,
      "pixelX": 2701.0467526103826,
      "pixelY": 735.7765657260169,
      "worldRotX": -0.98,
      "worldRotY": 0.1,
      "worldRotZ": 0.19,
      "facingDeg": 87.7974018382342,
      "screenshot": "/maps/spots/blizzard-world/mp7hmleu-816b.jpg",
      "capturedAt": "2026-05-16T00:10:31.463Z",
      "sourceFilename": "20260513170516_1.jpg"
    },
    {
      "id": "mp7hmll2-2bd8",
      "mapKey": "blizzard-world",
      "worldX": -39.12523328896277,
      "worldY": 0.92,
      "worldZ": 118.98636182632899,
      "pixelX": 2142.7257203328686,
      "pixelY": 1440.9862938332772,
      "worldRotX": -0.94,
      "worldRotY": 0.13,
      "worldRotZ": -0.3,
      "facingDeg": 110.91513577690044,
      "screenshot": "/maps/spots/blizzard-world/mp7hmll2-2bd8.jpg",
      "capturedAt": "2026-05-16T00:10:31.463Z",
      "sourceFilename": "20260513170334_1.jpg"
    },
    {
      "id": "mp7hmlrd-43dd",
      "mapKey": "blizzard-world",
      "worldX": -47.788483876455125,
      "worldY": 1.4,
      "worldZ": 86.13274081780925,
      "pixelX": 2351.919438386866,
      "pixelY": 2233.2704958628397,
      "worldRotX": -0.58,
      "worldRotY": 0.2,
      "worldRotZ": 0.79,
      "facingDeg": 34.76179784381095,
      "screenshot": "/maps/spots/blizzard-world/mp7hmlrd-43dd.jpg",
      "capturedAt": "2026-05-16T00:10:31.463Z",
      "sourceFilename": "20260513170257_1.jpg"
    },
    {
      "id": "mp7hmlx8-05fa",
      "mapKey": "blizzard-world",
      "worldX": -55.91268037861824,
      "worldY": 1.35,
      "worldZ": 104.08385190316187,
      "pixelX": 2523.0896880279947,
      "pixelY": 1814.0585865866026,
      "facingDeg": -164.57783868126134,
      "screenshot": "/maps/spots/blizzard-world/mp7hmlx8-05fa.jpg",
      "capturedAt": "2026-05-16T00:10:31.463Z",
      "sourceFilename": "20260513170240_1.jpg"
    },
    {
      "id": "mp7hmm3l-4e2d",
      "mapKey": "blizzard-world",
      "worldX": -59.54196840910027,
      "worldY": 1.4,
      "worldZ": 106.88780939205593,
      "pixelX": 2603.5835738580045,
      "pixelY": 1751.2647140267757,
      "worldRotX": -0.34,
      "worldRotY": 0.27,
      "worldRotZ": -0.9,
      "facingDeg": 149.4702941000659,
      "screenshot": "/maps/spots/blizzard-world/mp7hmm3l-4e2d.jpg",
      "capturedAt": "2026-05-16T00:10:31.463Z",
      "sourceFilename": "20260513170228_1.jpg"
    },
    {
      "id": "mp7hmm9m-af7a",
      "mapKey": "blizzard-world",
      "worldX": -59.81236565322824,
      "worldY": 2.2,
      "worldZ": 115.04738381793275,
      "pixelX": 2604.2513662631673,
      "pixelY": 1554.9404018283053,
      "worldRotX": 0.97,
      "worldRotY": 0.12,
      "worldRotZ": 0.22,
      "facingDeg": -95.52754015165618,
      "screenshot": "/maps/spots/blizzard-world/mp7hmm9m-af7a.jpg",
      "capturedAt": "2026-05-16T00:10:31.463Z",
      "sourceFilename": "20260513170219_1.jpg"
    },
    {
      "id": "mp7hmmfo-31c7",
      "mapKey": "blizzard-world",
      "worldX": -72.17190185543136,
      "worldY": 1.79,
      "worldZ": 106.26520594656505,
      "pixelX": 2895.959534782274,
      "pixelY": 1783.104552857189,
      "worldRotX": 0.67,
      "worldRotY": 0.05,
      "worldRotZ": -0.74,
      "facingDeg": -139.7636416907262,
      "screenshot": "/maps/spots/blizzard-world/mp7hmmfo-31c7.jpg",
      "capturedAt": "2026-05-16T00:10:31.463Z",
      "sourceFilename": "20260513170206_1.jpg"
    },
    {
      "id": "mp7hmmlj-1662",
      "mapKey": "blizzard-world",
      "worldX": -72.63,
      "worldY": 0.93,
      "worldZ": 71.92,
      "pixelX": 2933.1361242458133,
      "pixelY": 2633.812352139945,
      "worldRotX": 0.24,
      "worldRotY": 0.41,
      "worldRotZ": 0.88,
      "facingDeg": 5.710593137499643,
      "screenshot": "/maps/spots/blizzard-world/mp7hmmlj-1662.jpg",
      "capturedAt": "2026-05-16T00:10:31.463Z",
      "sourceFilename": "20260513170146_1.jpg"
    },
    {
      "id": "mp7hmmsm-a0ef",
      "mapKey": "blizzard-world",
      "worldX": -58.47100453703015,
      "worldY": 1.79,
      "worldZ": 69.14155705497868,
      "pixelX": 2604.5946336939674,
      "pixelY": 2669.1127822149956,
      "worldRotX": -0.99,
      "worldRotY": -0.03,
      "worldRotZ": 0.16,
      "facingDeg": 86.05935328963514,
      "screenshot": "/maps/spots/blizzard-world/mp7hmmsm-a0ef.jpg",
      "capturedAt": "2026-05-16T00:10:31.463Z",
      "sourceFilename": "20260513170119_1.jpg"
    },
    {
      "id": "mp7hmmyh-d2f4",
      "mapKey": "blizzard-world",
      "worldX": -56.281768114086034,
      "worldY": 0.85,
      "worldZ": 61.80017540571554,
      "pixelX": 2559.3162700800067,
      "pixelY": 2844.346063352627,
      "worldRotX": 0.98,
      "worldRotY": 0.14,
      "worldRotZ": 0.17,
      "facingDeg": -70.90650799951439,
      "screenshot": "/maps/spots/blizzard-world/mp7hmmyh-d2f4.jpg",
      "capturedAt": "2026-05-16T00:10:31.463Z",
      "sourceFilename": "20260513170103_1.jpg"
    },
    {
      "id": "mp7hmn4f-f8be",
      "mapKey": "blizzard-world",
      "worldX": -66.59146209453442,
      "worldY": 7.56,
      "worldZ": 78.34392318215238,
      "pixelX": 2786.1690581388393,
      "pixelY": 2460.6002528890326,
      "worldRotX": -0.73,
      "worldRotY": 0.08,
      "worldRotZ": -0.68,
      "facingDeg": 136.40126146090068,
      "screenshot": "/maps/spots/blizzard-world/mp7hmn4f-f8be.jpg",
      "capturedAt": "2026-05-16T00:10:31.463Z",
      "sourceFilename": "20260513170042_1.jpg"
    },
    {
      "id": "mp7hmnaz-fea9",
      "mapKey": "blizzard-world",
      "worldX": -46.961410534443665,
      "worldY": 6.22,
      "worldZ": 90.95346135547113,
      "pixelX": 2330.6132418996613,
      "pixelY": 2115.9585446692304,
      "worldRotX": -0.94,
      "worldRotY": 0.21,
      "worldRotZ": -0.29,
      "facingDeg": 118.4126614430726,
      "screenshot": "/maps/spots/blizzard-world/mp7hmnaz-fea9.jpg",
      "capturedAt": "2026-05-16T00:10:31.463Z",
      "sourceFilename": "20260513170030_1.jpg"
    },
    {
      "id": "mp7hmngs-5996",
      "mapKey": "blizzard-world",
      "worldX": -39.173285398963664,
      "worldY": 6.81,
      "worldZ": 92.93719227927556,
      "pixelX": 2157.9246500576696,
      "pixelY": 2055.721283670641,
      "worldRotX": -0.96,
      "worldRotY": 0.26,
      "worldRotZ": 0.06,
      "facingDeg": 93.36646066343006,
      "screenshot": "/maps/spots/blizzard-world/mp7hmngs-5996.jpg",
      "capturedAt": "2026-05-16T00:10:31.463Z",
      "sourceFilename": "20260513165643_1.jpg"
    },
    {
      "id": "mp7hmnmj-66fb",
      "mapKey": "blizzard-world",
      "worldX": -29.18961646278327,
      "worldY": 10.84,
      "worldZ": 93.56464504256229,
      "pixelX": 1942.1305473676468,
      "pixelY": 2025.070142708038,
      "worldRotX": 0.88,
      "worldRotY": -0.13,
      "worldRotZ": -0.46,
      "facingDeg": -116.89192489488792,
      "screenshot": "/maps/spots/blizzard-world/mp7hmnmj-66fb.jpg",
      "capturedAt": "2026-05-16T00:10:31.463Z",
      "sourceFilename": "20260513165628_1.jpg"
    },
    {
      "id": "mp7hmnsq-50d5",
      "mapKey": "blizzard-world",
      "worldX": -24.076921802547307,
      "worldY": 7.07,
      "worldZ": 95.96492423422784,
      "pixelX": 1832.5507496565785,
      "pixelY": 1961.1485940432483,
      "worldRotX": 0.87,
      "worldRotY": 0.05,
      "worldRotZ": -0.49,
      "facingDeg": -119.12792169417992,
      "screenshot": "/maps/spots/blizzard-world/mp7hmnsq-50d5.jpg",
      "capturedAt": "2026-05-16T00:10:31.463Z",
      "sourceFilename": "20260513165620_1.jpg"
    },
    {
      "id": "mp7hmnyl-10de",
      "mapKey": "blizzard-world",
      "worldX": -15.261220161881432,
      "worldY": 2.27,
      "worldZ": 113.67452711464419,
      "pixelX": 1641.3044895269322,
      "pixelY": 1541.200036569572,
      "worldRotX": 0.98,
      "worldRotY": 0.1,
      "worldRotZ": 0.19,
      "facingDeg": -101.94417718844635,
      "screenshot": "/maps/spots/blizzard-world/mp7hmnyl-10de.jpg",
      "capturedAt": "2026-05-16T00:10:31.463Z",
      "sourceFilename": "20260513165553_1.jpg"
    },
    {
      "id": "mp7hmo4z-246e",
      "mapKey": "blizzard-world",
      "worldX": 17.405712127602214,
      "worldY": 7.5,
      "worldZ": 76.80180527382609,
      "pixelX": 1001.0352851829549,
      "pixelY": 2331.2496665861954,
      "worldRotX": -0.86,
      "worldRotY": 0.1,
      "worldRotZ": -0.51,
      "facingDeg": 98.4269690214808,
      "screenshot": "/maps/spots/blizzard-world/mp7hmo4z-246e.jpg",
      "capturedAt": "2026-05-16T00:10:31.463Z",
      "sourceFilename": "20260513165534_1.jpg"
    },
    {
      "id": "mp7hmoap-477a",
      "mapKey": "blizzard-world",
      "worldX": 35.51180566483491,
      "worldY": 2.25,
      "worldZ": 83.1189067983652,
      "pixelX": 656.1475247020072,
      "pixelY": 2159.9631278238453,
      "worldRotX": -0.68,
      "worldRotY": 0.14,
      "worldRotZ": 0.72,
      "facingDeg": 53.76410082787799,
      "screenshot": "/maps/spots/blizzard-world/mp7hmoap-477a.jpg",
      "capturedAt": "2026-05-16T00:10:31.463Z",
      "sourceFilename": "20260513165520_1.jpg"
    },
    {
      "id": "mp7hmog9-643a",
      "mapKey": "blizzard-world",
      "worldX": 35.447385581762674,
      "worldY": 2.25,
      "worldZ": 82.92634546243026,
      "pixelX": 657.3760969388535,
      "pixelY": 2164.2987681245386,
      "worldRotX": -0.78,
      "worldRotY": -0.02,
      "worldRotZ": 0.62,
      "facingDeg": 49.538429614780114,
      "screenshot": "/maps/spots/blizzard-world/mp7hmog9-643a.jpg",
      "capturedAt": "2026-05-16T00:10:31.463Z",
      "sourceFilename": "20260513165513_1.jpg"
    },
    {
      "id": "mp7hmolu-2015",
      "mapKey": "blizzard-world",
      "worldX": 39.41962274072677,
      "worldY": 3.73,
      "worldZ": 68.09257839489973,
      "pixelX": 585.8101978510269,
      "pixelY": 2483.7774784741932,
      "worldRotX": 1,
      "worldRotY": 0.01,
      "worldRotZ": 0.01,
      "facingDeg": -98.64060641382397,
      "screenshot": "/maps/spots/blizzard-world/mp7hmolu-2015.jpg",
      "capturedAt": "2026-05-16T00:10:31.463Z",
      "sourceFilename": "20260513165326_1.jpg"
    },
    {
      "id": "mp7hmorh-94b1",
      "mapKey": "blizzard-world",
      "worldX": 44.11846717621247,
      "worldY": 3.72,
      "worldZ": 70.66669570667833,
      "pixelX": 498.9023205613754,
      "pixelY": 2418.302883738284,
      "worldRotX": -0.74,
      "worldRotY": 0.14,
      "worldRotZ": -0.66,
      "facingDeg": 107.5924245621816,
      "screenshot": "/maps/spots/blizzard-world/mp7hmorh-94b1.jpg",
      "capturedAt": "2026-05-16T00:10:31.463Z",
      "sourceFilename": "20260513165310_1.jpg"
    },
    {
      "id": "mp7hmox9-e262",
      "mapKey": "blizzard-world",
      "worldX": 54.24667271244189,
      "worldY": 3.59,
      "worldZ": 61.998609116030096,
      "pixelX": 315.8304778819328,
      "pixelY": 2587.9190918274085,
      "worldRotX": 0.56,
      "worldRotY": -0.02,
      "worldRotZ": -0.83,
      "facingDeg": -149.22732764611104,
      "screenshot": "/maps/spots/blizzard-world/mp7hmox9-e262.jpg",
      "capturedAt": "2026-05-16T00:10:31.463Z",
      "sourceFilename": "20260513165300_1.jpg"
    },
    {
      "id": "mp7hmp49-f33e",
      "mapKey": "blizzard-world",
      "worldX": 25.851808852140827,
      "worldY": 4.01,
      "worldZ": 70.18577487076664,
      "pixelX": 840.2978537755162,
      "pixelY": 2463.638938189715,
      "worldRotX": 0.99,
      "worldRotY": 0.16,
      "worldRotZ": 0.04,
      "facingDeg": -97.1250163489018,
      "screenshot": "/maps/spots/blizzard-world/mp7hmp49-f33e.jpg",
      "capturedAt": "2026-05-16T00:10:31.463Z",
      "sourceFilename": "20260513165246_1.jpg"
    },
    {
      "id": "mp7hmp9x-83bc",
      "mapKey": "blizzard-world",
      "worldX": 9.216079059852714,
      "worldY": 3.68,
      "worldZ": 65.06455731595308,
      "pixelX": 1164.2977279084632,
      "pixelY": 2613.1773416356914,
      "worldRotX": 0.01,
      "worldRotY": 0.01,
      "worldRotZ": -1,
      "facingDeg": 179.71446212539055,
      "screenshot": "/maps/spots/blizzard-world/mp7hmp9x-83bc.jpg",
      "capturedAt": "2026-05-16T00:10:31.463Z",
      "sourceFilename": "20260513165239_1.jpg"
    },
    {
      "id": "mp7hmpfi-f3e7",
      "mapKey": "blizzard-world",
      "worldX": 35.11512079031587,
      "worldY": 3.11,
      "worldZ": 35.88329437710484,
      "pixelX": 671.0220286269181,
      "pixelY": 3210.769141733609,
      "worldRotX": -0.13,
      "worldRotY": -0.05,
      "worldRotZ": 0.99,
      "facingDeg": 19.191287155396058,
      "screenshot": "/maps/spots/blizzard-world/mp7hmpfi-f3e7.jpg",
      "capturedAt": "2026-05-16T00:10:31.463Z",
      "sourceFilename": "20260513165222_1.jpg"
    },
    {
      "id": "mp7hmpm4-d2aa",
      "mapKey": "blizzard-world",
      "worldX": 33.65977504266837,
      "worldY": 7.46,
      "worldZ": 55.29583752186052,
      "pixelX": 695.2492969755561,
      "pixelY": 2779.646976415892,
      "worldRotX": -0.98,
      "worldRotY": -0.14,
      "worldRotZ": 0.13,
      "facingDeg": 77.24246783912334,
      "screenshot": "/maps/spots/blizzard-world/mp7hmpm4-d2aa.jpg",
      "capturedAt": "2026-05-16T00:10:31.463Z",
      "sourceFilename": "20260513165205_1.jpg"
    },
    {
      "id": "mp7hmpry-8faa",
      "mapKey": "blizzard-world",
      "worldX": -34.42226304135981,
      "worldY": 2.35,
      "worldZ": 53.34363702772183,
      "pixelX": 2075.4999455851002,
      "pixelY": 2992.8499169260062,
      "worldRotX": -0.46,
      "worldRotY": -0.07,
      "worldRotZ": -0.89,
      "facingDeg": 97.49585763973003,
      "screenshot": "/maps/spots/blizzard-world/mp7hmpry-8faa.jpg",
      "capturedAt": "2026-05-16T00:10:31.463Z",
      "sourceFilename": "20260513164917_1.jpg"
    },
    {
      "id": "mp7hmpxq-df34",
      "mapKey": "blizzard-world",
      "worldX": -27.893228656718613,
      "worldY": 1.28,
      "worldZ": 69.46920609213107,
      "pixelX": 1926.1275141031078,
      "pixelY": 2591.304464229679,
      "worldRotX": -0.71,
      "worldRotY": 0.06,
      "worldRotZ": 0.7,
      "facingDeg": 70.01774973020545,
      "screenshot": "/maps/spots/blizzard-world/mp7hmpxq-df34.jpg",
      "capturedAt": "2026-05-16T00:10:31.463Z",
      "sourceFilename": "20260513164902_1.jpg"
    },
    {
      "id": "mp7hmq3p-a55c",
      "mapKey": "blizzard-world",
      "worldX": -39.61439214630526,
      "worldY": 7.43,
      "worldZ": 52.754902820319444,
      "pixelX": 2189.8759936144115,
      "pixelY": 3021.1464371181874,
      "worldRotX": 0.62,
      "worldRotY": -0.02,
      "worldRotZ": 0.79,
      "facingDeg": -58.240519915187214,
      "screenshot": "/maps/spots/blizzard-world/mp7hmq3p-a55c.jpg",
      "capturedAt": "2026-05-16T00:10:31.463Z",
      "sourceFilename": "20260513164838_1.jpg"
    },
    {
      "id": "mp7hmq9h-2193",
      "mapKey": "blizzard-world",
      "worldX": -9.420065988403659,
      "worldY": 3.5,
      "worldZ": 56.42055131676326,
      "pixelX": 1543.4560649451776,
      "pixelY": 2855.5882820573715,
      "worldRotX": -0.98,
      "worldRotY": -0.06,
      "worldRotZ": 0.19,
      "facingDeg": 68.32535088097586,
      "screenshot": "/maps/spots/blizzard-world/mp7hmq9h-2193.jpg",
      "capturedAt": "2026-05-16T00:10:31.463Z",
      "sourceFilename": "20260513164821_1.jpg"
    },
    {
      "id": "mp7hmqfg-326d",
      "mapKey": "blizzard-world",
      "worldX": -17.832342298720192,
      "worldY": 8.74,
      "worldZ": 60.700547784722474,
      "pixelX": 1716.7867525775457,
      "pixelY": 2775.5121492832036,
      "worldRotX": -1,
      "worldRotY": -0.07,
      "worldRotZ": 0.06,
      "facingDeg": 112.76868481989743,
      "screenshot": "/maps/spots/blizzard-world/mp7hmqfg-326d.jpg",
      "capturedAt": "2026-05-16T00:10:31.463Z",
      "sourceFilename": "20260513164811_1.jpg"
    },
    {
      "id": "mp7hmqlb-43ed",
      "mapKey": "blizzard-world",
      "worldX": -1.2831951792919642,
      "worldY": 8.79,
      "worldZ": 45.28926154185983,
      "pixelX": 1380.8671937985011,
      "pixelY": 3094.4035276633103,
      "worldRotX": -0.93,
      "worldRotY": 0.24,
      "worldRotZ": 0.29,
      "facingDeg": 67.17556032498031,
      "screenshot": "/maps/spots/blizzard-world/mp7hmqlb-43ed.jpg",
      "capturedAt": "2026-05-16T00:10:31.463Z",
      "sourceFilename": "20260513164755_1.jpg"
    },
    {
      "id": "mp7hmqra-9778",
      "mapKey": "blizzard-world",
      "worldX": 10.681856311157254,
      "worldY": 1.02,
      "worldZ": 34.242954320882546,
      "pixelX": 1143.9219494364027,
      "pixelY": 3317.091884901957,
      "worldRotX": 0.99,
      "worldRotY": 0.03,
      "worldRotZ": 0.14,
      "facingDeg": -113.19859051364823,
      "screenshot": "/maps/spots/blizzard-world/mp7hmqra-9778.jpg",
      "capturedAt": "2026-05-16T00:10:31.463Z",
      "sourceFilename": "20260513164742_1.jpg"
    },
    {
      "id": "mp7hmqwz-7897",
      "mapKey": "blizzard-world",
      "worldX": 18.832028795864606,
      "worldY": -2.14,
      "worldZ": 11.416635271727658,
      "pixelX": 988.9740367502044,
      "pixelY": 3819.205018278897,
      "worldRotX": 0.17,
      "worldRotY": -0.06,
      "worldRotZ": 0.98,
      "facingDeg": -17.10272896905237,
      "screenshot": "/maps/spots/blizzard-world/mp7hmqwz-7897.jpg",
      "capturedAt": "2026-05-16T00:10:31.463Z",
      "sourceFilename": "20260513164730_1.jpg"
    },
    {
      "id": "mp7hmr3o-70ed",
      "mapKey": "blizzard-world",
      "worldX": 29.671553779368885,
      "worldY": -0.6,
      "worldZ": 9.080764810731615,
      "pixelX": 779.1655564917144,
      "pixelY": 3835.7090137813266,
      "worldRotX": -0.9,
      "worldRotY": -0.2,
      "worldRotZ": 0.39,
      "facingDeg": 46.273030020056744,
      "screenshot": "/maps/spots/blizzard-world/mp7hmr3o-70ed.jpg",
      "capturedAt": "2026-05-16T00:10:31.463Z",
      "sourceFilename": "20260513164722_1.jpg"
    },
    {
      "id": "mp7hmr9k-9e1c",
      "mapKey": "blizzard-world",
      "worldX": 30.96562041025808,
      "worldY": 1.22,
      "worldZ": 22.167521912974962,
      "pixelX": 752.0018380363414,
      "pixelY": 3532.885104502381,
      "worldRotX": -0.98,
      "worldRotY": 0.08,
      "worldRotZ": -0.18,
      "facingDeg": 94.51737093509239,
      "screenshot": "/maps/spots/blizzard-world/mp7hmr9k-9e1c.jpg",
      "capturedAt": "2026-05-16T00:10:31.463Z",
      "sourceFilename": "20260513164713_1.jpg"
    },
    {
      "id": "mp7hmrfh-96c7",
      "mapKey": "blizzard-world",
      "worldX": 20.276951947874238,
      "worldY": 1.97,
      "worldZ": 17.266398504794598,
      "pixelX": 959.2977919512723,
      "pixelY": 3679.1754729063446,
      "worldRotX": 0.84,
      "worldRotY": -0.07,
      "worldRotZ": 0.54,
      "facingDeg": -63.05425157149524,
      "screenshot": "/maps/spots/blizzard-world/mp7hmrfh-96c7.jpg",
      "capturedAt": "2026-05-16T00:10:31.463Z",
      "sourceFilename": "20260513164700_1.jpg"
    },
    {
      "id": "mp7hmrla-ef3f",
      "mapKey": "blizzard-world",
      "worldX": 13.343855509083031,
      "worldY": 2.92,
      "worldZ": 21.744324385660853,
      "pixelX": 1094.5473757656978,
      "pixelY": 3598.228121169224,
      "worldRotX": 0.08,
      "worldRotY": 0.13,
      "worldRotZ": -0.99,
      "facingDeg": -164.20759647114275,
      "screenshot": "/maps/spots/blizzard-world/mp7hmrla-ef3f.jpg",
      "capturedAt": "2026-05-16T00:10:31.463Z",
      "sourceFilename": "20260513164652_1.jpg"
    },
    {
      "id": "mp7hmrrj-b855",
      "mapKey": "blizzard-world",
      "worldX": -11.71172991462381,
      "worldY": 0.51,
      "worldZ": 16.446832649880307,
      "pixelX": 1606.8081417309088,
      "pixelY": 3807.751913863398,
      "facingDeg": 91.22539130237412,
      "screenshot": "/maps/spots/blizzard-world/mp7hmrrj-b855.jpg",
      "capturedAt": "2026-05-16T00:10:31.463Z",
      "sourceFilename": "20260513164630_1.jpg"
    },
    {
      "id": "mp7hmrx3-bc58",
      "mapKey": "blizzard-world",
      "worldX": -11.413761226864791,
      "worldY": -0.92,
      "worldZ": 16.328544274766685,
      "pixelX": 1600.6125572948945,
      "pixelY": 3809.5220808451163,
      "worldRotX": -0.99,
      "worldRotY": 0.07,
      "worldRotZ": 0.14,
      "facingDeg": 88.55587446906416,
      "screenshot": "/maps/spots/blizzard-world/mp7hmrx3-bc58.jpg",
      "capturedAt": "2026-05-16T00:10:31.463Z",
      "sourceFilename": "20260513164627_1.jpg"
    },
    {
      "id": "mp7hms2u-c5c3",
      "mapKey": "blizzard-world",
      "worldX": -12.709046104282535,
      "worldY": -1.66,
      "worldZ": 0.6238132104803638,
      "pixelX": 1634.2288753302855,
      "pixelY": 4191.643048594023,
      "worldRotX": -1,
      "worldRotY": 0.09,
      "worldRotZ": -0.03,
      "facingDeg": 85.43564717346261,
      "screenshot": "/maps/spots/blizzard-world/mp7hms2u-c5c3.jpg",
      "capturedAt": "2026-05-16T00:10:31.463Z",
      "sourceFilename": "20260513164616_1.jpg"
    },
    {
      "id": "mp7hms8o-100e",
      "mapKey": "blizzard-world",
      "worldX": 10.98065586634511,
      "worldY": 2.43,
      "worldZ": 0.9665653623892533,
      "pixelX": 1147.3108687564118,
      "pixelY": 4091.2826956935673,
      "worldRotX": -0.84,
      "worldRotY": 0.2,
      "worldRotZ": 0.5,
      "facingDeg": 44.90773634462339,
      "screenshot": "/maps/spots/blizzard-world/mp7hms8o-100e.jpg",
      "capturedAt": "2026-05-16T00:10:31.463Z",
      "sourceFilename": "20260513164604_1.jpg"
    },
    {
      "id": "mp7hmsel-1723",
      "mapKey": "blizzard-world",
      "worldX": 15.835070497533374,
      "worldY": 1.07,
      "worldZ": -1.3398884200428,
      "pixelX": 1051.2538043747334,
      "pixelY": 4126.890027493921,
      "worldRotX": 0.98,
      "worldRotY": 0.03,
      "worldRotZ": -0.21,
      "facingDeg": -91.66028236898245,
      "screenshot": "/maps/spots/blizzard-world/mp7hmsel-1723.jpg",
      "capturedAt": "2026-05-16T00:10:31.463Z",
      "sourceFilename": "20260513164549_1.jpg"
    },
    {
      "id": "mp7hmslv-b973",
      "mapKey": "blizzard-world",
      "worldX": 16.278717963548136,
      "worldY": -3.84,
      "worldZ": 1.1166143764266105,
      "pixelX": 1041.8394718961952,
      "pixelY": 4067.834476766559,
      "worldRotX": 0.05,
      "worldRotY": 0.39,
      "worldRotZ": 0.92,
      "facingDeg": -3.2475479390000626,
      "screenshot": "/maps/spots/blizzard-world/mp7hmslv-b973.jpg",
      "capturedAt": "2026-05-16T00:10:31.463Z",
      "sourceFilename": "20260513164540_1.jpg"
    },
    {
      "id": "mp7hmsrs-8add",
      "mapKey": "blizzard-world",
      "worldX": 13.674981405115306,
      "worldY": -0.86,
      "worldZ": -4.828045784203666,
      "pixelX": 1095.098342370001,
      "pixelY": 4216.951769000123,
      "worldRotX": 0.87,
      "worldRotY": 0.15,
      "worldRotZ": -0.48,
      "facingDeg": -142.89404103147996,
      "screenshot": "/maps/spots/blizzard-world/mp7hmsrs-8add.jpg",
      "capturedAt": "2026-05-16T00:10:31.463Z",
      "sourceFilename": "20260513163023_1.jpg"
    },
    {
      "id": "mp7hmsy4-470b",
      "mapKey": "blizzard-world",
      "worldX": -11.221380263080196,
      "worldY": -1.54,
      "worldZ": 0.840451815587104,
      "pixelX": 1602.809154855472,
      "pixelY": 4180.48299137345,
      "worldRotX": -0.06,
      "worldRotY": -0.02,
      "worldRotZ": -1,
      "facingDeg": 176.09148794896038,
      "screenshot": "/maps/spots/blizzard-world/mp7hmsy4-470b.jpg",
      "capturedAt": "2026-05-16T00:10:31.463Z",
      "sourceFilename": "20260513162946_1.jpg"
    },
    {
      "id": "mp7hmt44-6d53",
      "mapKey": "blizzard-world",
      "worldX": -8.692976619335104,
      "worldY": -2,
      "worldZ": -0.47374106868277405,
      "pixelX": 1550.3112070354298,
      "pixelY": 4202.020610991929,
      "worldRotX": -0.99,
      "worldRotY": 0.17,
      "worldRotZ": -0.04,
      "facingDeg": 84.68010608219315,
      "screenshot": "/maps/spots/blizzard-world/mp7hmt44-6d53.jpg",
      "capturedAt": "2026-05-16T00:10:31.463Z",
      "sourceFilename": "20260513162935_1.jpg"
    },
    {
      "id": "mp7hmta2-6893",
      "mapKey": "blizzard-world",
      "worldX": 1.094778866614657,
      "worldY": 0.21,
      "worldZ": -10.178231316218024,
      "pixelX": 1351.0882255645,
      "pixelY": 4394.513086332084,
      "worldRotX": -0.01,
      "worldRotY": 0.32,
      "worldRotZ": 0.95,
      "facingDeg": -4.398705354995532,
      "screenshot": "/maps/spots/blizzard-world/mp7hmta2-6893.jpg",
      "capturedAt": "2026-05-16T00:10:31.463Z",
      "sourceFilename": "20260513162101_1.jpg"
    },
    {
      "id": "mp7hmtgu-c4af",
      "mapKey": "blizzard-world",
      "worldX": 4.037882165515417,
      "worldY": -1.22,
      "worldZ": -21.52132608095289,
      "pixelX": 1294.5519740659927,
      "pixelY": 4652.964521753831,
      "worldRotX": 0.01,
      "worldRotY": -0.61,
      "worldRotZ": 0.79,
      "facingDeg": -1.3581794996405825,
      "screenshot": "/maps/spots/blizzard-world/mp7hmtgu-c4af.jpg",
      "capturedAt": "2026-05-16T00:10:31.463Z",
      "sourceFilename": "20260513162045_1.jpg"
    },
    {
      "id": "mp7hmu5m-0b11",
      "mapKey": "blizzard-world",
      "worldX": 1.0957067507395926,
      "worldY": -1.78,
      "worldZ": -10.234765933795188,
      "pixelX": 1351.0882255645,
      "pixelY": 4395.859187558239,
      "worldRotX": 0.02,
      "worldRotY": 0.03,
      "worldRotZ": -1,
      "facingDeg": -179.8050652748782,
      "screenshot": "/maps/spots/blizzard-world/mp7hmu5m-0b11.jpg",
      "capturedAt": "2026-05-16T00:10:31.463Z",
      "sourceFilename": "20260513161748_1.jpg"
    },
    {
      "id": "mp7hmuca-a0ee",
      "mapKey": "blizzard-world",
      "worldX": -47.46513162313529,
      "worldY": 4.07,
      "worldZ": 116.83390419718387,
      "pixelX": 2326.4051302732396,
      "pixelY": 1499.6269816013025,
      "worldRotX": -0.73,
      "worldRotY": -0.05,
      "worldRotZ": -0.68,
      "facingDeg": 130.710846671181,
      "screenshot": "/maps/spots/blizzard-world/mp7hmuca-a0ee.jpg",
      "capturedAt": "2026-05-16T00:10:31.463Z",
      "sourceFilename": "20260513161722_1.jpg"
    }
  ]
}